[ {
  "Date" : "26/12/2020",
  "Hour" : "24:00"
}, {
  "Date" : "26/12/2020",
  "Hour" : "23:00"
}, {
  "Date" : "26/12/2020",
  "Hour" : "22:00"
}, {
  "Date" : "26/12/2020",
  "Hour" : "21:00"
}, {
  "Date" : "26/12/2020",
  "Hour" : "20:00"
}, {
  "Date" : "26/12/2020",
  "Hour" : "19:00",
  "NOgm3" : "0",
  "NO2" : "9",
  "NO2ICA" : "Muy bueno / Oso ona",
  "NOXgm3" : "9",
  "O3gm3" : "62",
  "OZONO" : "62",
  "O3ICA" : "Muy bueno / Oso ona",
  "O38hgm3" : "61",
  "Dviengrados" : "301",
  "H" : "98",
  "PmBar" : "976,4",
  "Rwm2" : "0",
  "TC" : "4,2",
  "Vvienms" : "3,87",
  "ICAEstacion" : "Muy bueno / Oso ona"
}, {
  "Date" : "26/12/2020",
  "Hour" : "18:00",
  "NOgm3" : "0",
  "NO2" : "6",
  "NO2ICA" : "Muy bueno / Oso ona",
  "NOXgm3" : "6",
  "O3ICA" : "Sin datos / Daturik gabe",
  "O38hgm3" : "60",
  "Dviengrados" : "316",
  "H" : "97",
  "PmBar" : "976,9",
  "Rwm2" : "0",
  "TC" : "4,3",
  "Vvienms" : "5,27",
  "ICAEstacion" : "Muy bueno / Oso ona"
}, {
  "Date" : "26/12/2020",
  "Hour" : "17:00",
  "NOgm3" : "0",
  "NO2" : "7",
  "NO2ICA" : "Muy bueno / Oso ona",
  "NOXgm3" : "7",
  "O3gm3" : "65",
  "OZONO" : "65",
  "O3ICA" : "Muy bueno / Oso ona",
  "O38hgm3" : "61",
  "Dviengrados" : "309",
  "H" : "95",
  "PmBar" : "977,5",
  "Rwm2" : "2,4",
  "TC" : "4,7",
  "Vvienms" : "4,01",
  "ICAEstacion" : "Muy bueno / Oso ona"
}, {
  "Date" : "26/12/2020",
  "Hour" : "16:00",
  "NOgm3" : "0",
  "NO2" : "6",
  "NO2ICA" : "Muy bueno / Oso ona",
  "NOXgm3" : "6",
  "O3gm3" : "65",
  "OZONO" : "65",
  "O3ICA" : "Muy bueno / Oso ona",
  "O38hgm3" : "62",
  "Dviengrados" : "313",
  "H" : "94",
  "PmBar" : "978,1",
  "Rwm2" : "29,9",
  "TC" : "4,8",
  "Vvienms" : "4,16",
  "ICAEstacion" : "Muy bueno / Oso ona"
}, {
  "Date" : "26/12/2020",
  "Hour" : "15:00",
  "NOgm3" : "0",
  "NO2" : "5",
  "NO2ICA" : "Muy bueno / Oso ona",
  "NOXgm3" : "5",
  "O3gm3" : "66",
  "OZONO" : "66",
  "O3ICA" : "Muy bueno / Oso ona",
  "O38hgm3" : "61",
  "Dviengrados" : "331",
  "H" : "93",
  "PmBar" : "978,5",
  "Rwm2" : "95,8",
  "TC" : "4,8",
  "Vvienms" : "3,74",
  "ICAEstacion" : "Muy bueno / Oso ona"
}, {
  "Date" : "26/12/2020",
  "Hour" : "14:00",
  "NOgm3" : "0",
  "NO2" : "6",
  "NO2ICA" : "Muy bueno / Oso ona",
  "NOXgm3" : "6",
  "O3gm3" : "65",
  "OZONO" : "65",
  "O3ICA" : "Muy bueno / Oso ona",
  "O38hgm3" : "62",
  "Dviengrados" : "342",
  "H" : "96",
  "PmBar" : "979,1",
  "Rwm2" : "54,4",
  "TC" : "4,2",
  "Vvienms" : "4,7",
  "ICAEstacion" : "Muy bueno / Oso ona"
}, {
  "Date" : "26/12/2020",
  "Hour" : "13:00",
  "NOgm3" : "0",
  "NO2" : "10",
  "NO2ICA" : "Muy bueno / Oso ona",
  "NOXgm3" : "10",
  "O3gm3" : "60",
  "OZONO" : "60",
  "O3ICA" : "Muy bueno / Oso ona",
  "O38hgm3" : "63",
  "Dviengrados" : "321",
  "H" : "95",
  "PmBar" : "979,7",
  "Rwm2" : "44,2",
  "TC" : "4,2",
  "Vvienms" : "3,08",
  "ICAEstacion" : "Muy bueno / Oso ona"
}, {
  "Date" : "26/12/2020",
  "Hour" : "12:00",
  "NOgm3" : "0",
  "NO2" : "7",
  "NO2ICA" : "Muy bueno / Oso ona",
  "NOXgm3" : "7",
  "O3gm3" : "53",
  "OZONO" : "53",
  "O3ICA" : "Muy bueno / Oso ona",
  "O38hgm3" : "65",
  "Dviengrados" : "40",
  "H" : "91",
  "PmBar" : "980,4",
  "Rwm2" : "45,4",
  "TC" : "4,4",
  "Vvienms" : "1,35",
  "ICAEstacion" : "Muy bueno / Oso ona"
}, {
  "Date" : "26/12/2020",
  "Hour" : "11:00",
  "NOgm3" : "0",
  "NO2" : "6",
  "NO2ICA" : "Muy bueno / Oso ona",
  "NOXgm3" : "6",
  "O3gm3" : "54",
  "OZONO" : "54",
  "O3ICA" : "Muy bueno / Oso ona",
  "O38hgm3" : "68",
  "Dviengrados" : "27",
  "H" : "87",
  "PmBar" : "980,8",
  "Rwm2" : "46,8",
  "TC" : "4,8",
  "Vvienms" : "2,04",
  "ICAEstacion" : "Muy bueno / Oso ona"
}, {
  "Date" : "26/12/2020",
  "Hour" : "10:00",
  "NOgm3" : "0",
  "NO2" : "6",
  "NO2ICA" : "Muy bueno / Oso ona",
  "NOXgm3" : "6",
  "O3gm3" : "58",
  "OZONO" : "58",
  "O3ICA" : "Muy bueno / Oso ona",
  "O38hgm3" : "69",
  "Dviengrados" : "14",
  "H" : "88",
  "PmBar" : "980,7",
  "Rwm2" : "46,1",
  "TC" : "4,7",
  "Vvienms" : "2,21",
  "ICAEstacion" : "Muy bueno / Oso ona"
} ]