[ {
  "Date" : "18/01/2021",
  "Hour" : "24:00"
}, {
  "Date" : "18/01/2021",
  "Hour" : "23:00"
}, {
  "Date" : "18/01/2021",
  "Hour" : "22:00"
}, {
  "Date" : "18/01/2021",
  "Hour" : "21:00"
}, {
  "Date" : "18/01/2021",
  "Hour" : "20:00"
}, {
  "Date" : "18/01/2021",
  "Hour" : "19:00"
}, {
  "Date" : "18/01/2021",
  "Hour" : "18:00"
}, {
  "Date" : "18/01/2021",
  "Hour" : "17:00"
}, {
  "Date" : "18/01/2021",
  "Hour" : "16:00"
}, {
  "Date" : "18/01/2021",
  "Hour" : "15:00",
  "COmgm3" : "0,28",
  "CO8hmgm3" : "0,38",
  "NOgm3" : "17",
  "NO2" : "39",
  "NO2ICA" : "Muy bueno / Oso ona",
  "NOXgm3" : "64",
  "PM10" : "14,92",
  "PM10ICA" : "Muy bueno / Oso ona",
  "PM25" : "11,79",
  "PM25ICA" : "Bueno / Ona",
  "SO2" : "10",
  "SO2ICA" : "Muy bueno / Oso ona",
  "Dviengrados" : "341",
  "H" : "84",
  "TC" : "13,1",
  "Vvienms" : "0,67",
  "ICAEstacion" : "Bueno / Ona"
}, {
  "Date" : "18/01/2021",
  "Hour" : "14:00",
  "COmgm3" : "0,29",
  "CO8hmgm3" : "0,5",
  "NOgm3" : "11",
  "NO2" : "29",
  "NO2ICA" : "Muy bueno / Oso ona",
  "NOXgm3" : "45",
  "PM10" : "14,46",
  "PM10ICA" : "Muy bueno / Oso ona",
  "PM25" : "11,63",
  "PM25ICA" : "Bueno / Ona",
  "SO2" : "6",
  "SO2ICA" : "Muy bueno / Oso ona",
  "Dviengrados" : "341",
  "H" : "85",
  "TC" : "12,9",
  "Vvienms" : "0,57",
  "ICAEstacion" : "Bueno / Ona"
}, {
  "Date" : "18/01/2021",
  "Hour" : "13:00",
  "COmgm3" : "0,28",
  "CO8hmgm3" : "0,61",
  "NOgm3" : "13",
  "NO2" : "33",
  "NO2ICA" : "Muy bueno / Oso ona",
  "NOXgm3" : "53",
  "PM10" : "14,29",
  "PM10ICA" : "Muy bueno / Oso ona",
  "PM25" : "11,54",
  "PM25ICA" : "Bueno / Ona",
  "SO2" : "5",
  "SO2ICA" : "Muy bueno / Oso ona",
  "Dviengrados" : "10",
  "H" : "84",
  "TC" : "13,2",
  "Vvienms" : "0,56",
  "ICAEstacion" : "Bueno / Ona"
}, {
  "Date" : "18/01/2021",
  "Hour" : "12:00",
  "COmgm3" : "0,3",
  "CO8hmgm3" : "0,69",
  "NOgm3" : "29",
  "NO2" : "41",
  "NO2ICA" : "Bueno / Ona",
  "NOXgm3" : "84",
  "PM10" : "13,88",
  "PM10ICA" : "Muy bueno / Oso ona",
  "PM25" : "11,29",
  "PM25ICA" : "Bueno / Ona",
  "SO2" : "4",
  "SO2ICA" : "Muy bueno / Oso ona",
  "Dviengrados" : "16",
  "H" : "90",
  "TC" : "12,2",
  "Vvienms" : "0,71",
  "ICAEstacion" : "Bueno / Ona"
}, {
  "Date" : "18/01/2021",
  "Hour" : "11:00",
  "COmgm3" : "0,43",
  "CO8hmgm3" : "0,68",
  "NOgm3" : "47",
  "NO2" : "49",
  "NO2ICA" : "Bueno / Ona",
  "NOXgm3" : "119",
  "PM10" : "13",
  "PM10ICA" : "Muy bueno / Oso ona",
  "PM25ICA" : "Sin datos / Daturik gabe",
  "SO2" : "4",
  "SO2ICA" : "Muy bueno / Oso ona",
  "Dviengrados" : "17",
  "H" : "94",
  "TC" : "10,9",
  "Vvienms" : "0,8",
  "ICAEstacion" : "Bueno / Ona"
}, {
  "Date" : "18/01/2021",
  "Hour" : "10:00",
  "COmgm3" : "0,47",
  "CO8hmgm3" : "0,65",
  "NOgm3" : "79",
  "NO2" : "59",
  "NO2ICA" : "Bueno / Ona",
  "NOXgm3" : "178",
  "PM10" : "12,21",
  "PM10ICA" : "Muy bueno / Oso ona",
  "PM25ICA" : "Sin datos / Daturik gabe",
  "SO2" : "5",
  "SO2ICA" : "Muy bueno / Oso ona",
  "Dviengrados" : "37",
  "H" : "96",
  "TC" : "9,8",
  "Vvienms" : "0,68",
  "ICAEstacion" : "Bueno / Ona"
}, {
  "Date" : "18/01/2021",
  "Hour" : "09:00",
  "COmgm3" : "0,48",
  "CO8hmgm3" : "0,62",
  "NOgm3" : "47",
  "NO2" : "61",
  "NO2ICA" : "Bueno / Ona",
  "NOXgm3" : "132",
  "PM10" : "11,42",
  "PM10ICA" : "Muy bueno / Oso ona",
  "PM25" : "9,63",
  "PM25ICA" : "Muy bueno / Oso ona",
  "SO2" : "4",
  "SO2ICA" : "Muy bueno / Oso ona",
  "Dviengrados" : "235",
  "H" : "95",
  "TC" : "9,6",
  "Vvienms" : "0,12",
  "ICAEstacion" : "Bueno / Ona"
}, {
  "Date" : "18/01/2021",
  "Hour" : "08:00",
  "COmgm3" : "0,51",
  "CO8hmgm3" : "0,59",
  "NOgm3" : "41",
  "NO2" : "58",
  "NO2ICA" : "Bueno / Ona",
  "NOXgm3" : "120",
  "PM10" : "10,79",
  "PM10ICA" : "Muy bueno / Oso ona",
  "PM25" : "9,13",
  "PM25ICA" : "Muy bueno / Oso ona",
  "SO2" : "4",
  "SO2ICA" : "Muy bueno / Oso ona",
  "Dviengrados" : "354",
  "H" : "95",
  "TC" : "9,3",
  "Vvienms" : "0,41",
  "ICAEstacion" : "Bueno / Ona"
}, {
  "Date" : "18/01/2021",
  "Hour" : "07:00",
  "COmgm3" : "1,23",
  "CO8hmgm3" : "0,56",
  "NOgm3" : "13",
  "NO2" : "44",
  "NO2ICA" : "Bueno / Ona",
  "NOXgm3" : "63",
  "PM10" : "10,38",
  "PM10ICA" : "Muy bueno / Oso ona",
  "PM25" : "8,71",
  "PM25ICA" : "Muy bueno / Oso ona",
  "SO2" : "4",
  "SO2ICA" : "Muy bueno / Oso ona",
  "Dviengrados" : "18",
  "H" : "99",
  "TC" : "8,9",
  "Vvienms" : "0,5",
  "ICAEstacion" : "Bueno / Ona"
}, {
  "Date" : "18/01/2021",
  "Hour" : "06:00",
  "COmgm3" : "1,18",
  "CO8hmgm3" : "0,48",
  "NOgm3" : "3",
  "NO2" : "32",
  "NO2ICA" : "Muy bueno / Oso ona",
  "NOXgm3" : "36",
  "PM10" : "10,13",
  "PM10ICA" : "Muy bueno / Oso ona",
  "PM25" : "8,42",
  "PM25ICA" : "Muy bueno / Oso ona",
  "SO2" : "3",
  "SO2ICA" : "Muy bueno / Oso ona",
  "Dviengrados" : "33",
  "H" : "98",
  "TC" : "9,4",
  "Vvienms" : "0,21",
  "ICAEstacion" : "Muy bueno / Oso ona"
}, {
  "Date" : "18/01/2021",
  "Hour" : "05:00",
  "COmgm3" : "0,94",
  "CO8hmgm3" : "0,38",
  "NOgm3" : "1",
  "NO2" : "25",
  "NO2ICA" : "Muy bueno / Oso ona",
  "NOXgm3" : "27",
  "PM10" : "9,75",
  "PM10ICA" : "Muy bueno / Oso ona",
  "PM25" : "8,04",
  "PM25ICA" : "Muy bueno / Oso ona",
  "SO2" : "3",
  "SO2ICA" : "Muy bueno / Oso ona",
  "Dviengrados" : "29",
  "H" : "100",
  "TC" : "8,3",
  "Vvienms" : "0,73",
  "ICAEstacion" : "Muy bueno / Oso ona"
}, {
  "Date" : "18/01/2021",
  "Hour" : "04:00",
  "COmgm3" : "0,23",
  "CO8hmgm3" : "0,33",
  "NOgm3" : "0",
  "NO2" : "13",
  "NO2ICA" : "Muy bueno / Oso ona",
  "NOXgm3" : "13",
  "PM10" : "9,54",
  "PM10ICA" : "Muy bueno / Oso ona",
  "PM25" : "7,83",
  "PM25ICA" : "Muy bueno / Oso ona",
  "SO2" : "3",
  "SO2ICA" : "Muy bueno / Oso ona",
  "Dviengrados" : "19",
  "H" : "96",
  "TC" : "9,2",
  "Vvienms" : "0,23",
  "ICAEstacion" : "Muy bueno / Oso ona"
}, {
  "Date" : "18/01/2021",
  "Hour" : "03:00",
  "COmgm3" : "0,2",
  "CO8hmgm3" : "0,35",
  "NOgm3" : "0",
  "NO2" : "11",
  "NO2ICA" : "Muy bueno / Oso ona",
  "NOXgm3" : "11",
  "PM10" : "9,46",
  "PM10ICA" : "Muy bueno / Oso ona",
  "PM25" : "7,67",
  "PM25ICA" : "Muy bueno / Oso ona",
  "SO2" : "3",
  "SO2ICA" : "Muy bueno / Oso ona",
  "Dviengrados" : "18",
  "H" : "96",
  "TC" : "9,2",
  "Vvienms" : "0,49",
  "ICAEstacion" : "Muy bueno / Oso ona"
}, {
  "Date" : "18/01/2021",
  "Hour" : "02:00",
  "COmgm3" : "0,22",
  "CO8hmgm3" : "0,37",
  "NOgm3" : "0",
  "NO2" : "8",
  "NO2ICA" : "Muy bueno / Oso ona",
  "NOXgm3" : "8",
  "PM10" : "9,63",
  "PM10ICA" : "Muy bueno / Oso ona",
  "PM25" : "7,79",
  "PM25ICA" : "Muy bueno / Oso ona",
  "SO2" : "3",
  "SO2ICA" : "Muy bueno / Oso ona",
  "Dviengrados" : "29",
  "H" : "97",
  "TC" : "8,9",
  "Vvienms" : "0,55",
  "ICAEstacion" : "Muy bueno / Oso ona"
}, {
  "Date" : "18/01/2021",
  "Hour" : "01:00",
  "COmgm3" : "0,21",
  "CO8hmgm3" : "0,39",
  "NOgm3" : "0",
  "NO2" : "8",
  "NO2ICA" : "Muy bueno / Oso ona",
  "NOXgm3" : "8",
  "PM10" : "9,88",
  "PM10ICA" : "Muy bueno / Oso ona",
  "PM25" : "8,04",
  "PM25ICA" : "Muy bueno / Oso ona",
  "SO2" : "3",
  "SO2ICA" : "Muy bueno / Oso ona",
  "Dviengrados" : "111",
  "H" : "95",
  "TC" : "9,6",
  "Vvienms" : "0,57",
  "ICAEstacion" : "Muy bueno / Oso ona"
}, {
  "Date" : "17/01/2021",
  "Hour" : "24:00",
  "COmgm3" : "0,23",
  "CO8hmgm3" : "0,41",
  "NOgm3" : "0",
  "NO2" : "7",
  "NO2ICA" : "Muy bueno / Oso ona",
  "NOXgm3" : "7",
  "PM10" : "10",
  "PM10ICA" : "Muy bueno / Oso ona",
  "PM25" : "8,13",
  "PM25ICA" : "Muy bueno / Oso ona",
  "SO2" : "3",
  "SO2ICA" : "Muy bueno / Oso ona",
  "Dviengrados" : "57",
  "H" : "95",
  "TC" : "9,6",
  "Vvienms" : "0,63",
  "ICAEstacion" : "Muy bueno / Oso ona"
}, {
  "Date" : "17/01/2021",
  "Hour" : "23:00",
  "COmgm3" : "0,65",
  "CO8hmgm3" : "0,43",
  "NOgm3" : "0",
  "NO2" : "10",
  "NO2ICA" : "Muy bueno / Oso ona",
  "NOXgm3" : "10",
  "PM10" : "10,29",
  "PM10ICA" : "Muy bueno / Oso ona",
  "PM25" : "8,33",
  "PM25ICA" : "Muy bueno / Oso ona",
  "SO2" : "3",
  "SO2ICA" : "Muy bueno / Oso ona",
  "Dviengrados" : "3",
  "H" : "97",
  "TC" : "9,8",
  "Vvienms" : "0,52",
  "ICAEstacion" : "Muy bueno / Oso ona"
}, {
  "Date" : "17/01/2021",
  "Hour" : "22:00",
  "COmgm3" : "0,39",
  "CO8hmgm3" : "0,4",
  "NOgm3" : "0",
  "NO2" : "16",
  "NO2ICA" : "Muy bueno / Oso ona",
  "NOXgm3" : "16",
  "PM10" : "10,38",
  "PM10ICA" : "Muy bueno / Oso ona",
  "PM25" : "8,33",
  "PM25ICA" : "Muy bueno / Oso ona",
  "SO2" : "3",
  "SO2ICA" : "Muy bueno / Oso ona",
  "Dviengrados" : "14",
  "H" : "97",
  "TC" : "9,9",
  "Vvienms" : "0,57",
  "ICAEstacion" : "Muy bueno / Oso ona"
}, {
  "Date" : "17/01/2021",
  "Hour" : "21:00",
  "COmgm3" : "0,48",
  "CO8hmgm3" : "0,39",
  "NOgm3" : "0",
  "NO2" : "16",
  "NO2ICA" : "Muy bueno / Oso ona",
  "NOXgm3" : "16",
  "PM10" : "10,71",
  "PM10ICA" : "Muy bueno / Oso ona",
  "PM25" : "8,5",
  "PM25ICA" : "Muy bueno / Oso ona",
  "SO2" : "4",
  "SO2ICA" : "Muy bueno / Oso ona",
  "Dviengrados" : "17",
  "H" : "97",
  "TC" : "10,1",
  "Vvienms" : "0,53",
  "ICAEstacion" : "Muy bueno / Oso ona"
}, {
  "Date" : "17/01/2021",
  "Hour" : "20:00",
  "COmgm3" : "0,39",
  "CO8hmgm3" : "0,37",
  "NOgm3" : "1",
  "NO2" : "22",
  "NO2ICA" : "Muy bueno / Oso ona",
  "NOXgm3" : "23",
  "PM10" : "11,38",
  "PM10ICA" : "Muy bueno / Oso ona",
  "PM25" : "8,92",
  "PM25ICA" : "Muy bueno / Oso ona",
  "SO2" : "4",
  "SO2ICA" : "Muy bueno / Oso ona",
  "Dviengrados" : "18",
  "H" : "98",
  "TC" : "10,2",
  "Vvienms" : "0,57",
  "ICAEstacion" : "Muy bueno / Oso ona"
}, {
  "Date" : "17/01/2021",
  "Hour" : "19:00",
  "COmgm3" : "0,4",
  "CO8hmgm3" : "0,36",
  "NOgm3" : "16",
  "NO2" : "46",
  "NO2ICA" : "Bueno / Ona",
  "NOXgm3" : "70",
  "PM10" : "11,5",
  "PM10ICA" : "Muy bueno / Oso ona",
  "PM25" : "8,83",
  "PM25ICA" : "Muy bueno / Oso ona",
  "SO2" : "5",
  "SO2ICA" : "Muy bueno / Oso ona",
  "Dviengrados" : "11",
  "H" : "99",
  "TC" : "11",
  "Vvienms" : "0,36",
  "ICAEstacion" : "Bueno / Ona"
}, {
  "Date" : "17/01/2021",
  "Hour" : "18:00",
  "COmgm3" : "0,39",
  "CO8hmgm3" : "0,34",
  "NOgm3" : "12",
  "NO2" : "49",
  "NO2ICA" : "Bueno / Ona",
  "NOXgm3" : "67",
  "PM10" : "11,88",
  "PM10ICA" : "Muy bueno / Oso ona",
  "PM25" : "8,88",
  "PM25ICA" : "Muy bueno / Oso ona",
  "SO2" : "4",
  "SO2ICA" : "Muy bueno / Oso ona",
  "Dviengrados" : "141",
  "H" : "99",
  "TC" : "10,8",
  "Vvienms" : "0,31",
  "ICAEstacion" : "Bueno / Ona"
}, {
  "Date" : "17/01/2021",
  "Hour" : "17:00",
  "COmgm3" : "0,4",
  "CO8hmgm3" : "0,32",
  "NOgm3" : "9",
  "NO2" : "49",
  "NO2ICA" : "Bueno / Ona",
  "NOXgm3" : "62",
  "PM10" : "12,04",
  "PM10ICA" : "Muy bueno / Oso ona",
  "PM25" : "8,79",
  "PM25ICA" : "Muy bueno / Oso ona",
  "SO2" : "4",
  "SO2ICA" : "Muy bueno / Oso ona",
  "Dviengrados" : "157",
  "H" : "98",
  "TC" : "10,7",
  "Vvienms" : "0,62",
  "ICAEstacion" : "Bueno / Ona"
}, {
  "Date" : "17/01/2021",
  "Hour" : "16:00",
  "COmgm3" : "0,36",
  "CO8hmgm3" : "0,3",
  "NOgm3" : "9",
  "NO2" : "41",
  "NO2ICA" : "Bueno / Ona",
  "NOXgm3" : "54",
  "PM10" : "12,38",
  "PM10ICA" : "Muy bueno / Oso ona",
  "PM25" : "8,83",
  "PM25ICA" : "Muy bueno / Oso ona",
  "SO2" : "6",
  "SO2ICA" : "Muy bueno / Oso ona",
  "Dviengrados" : "165",
  "H" : "99",
  "TC" : "10,6",
  "Vvienms" : "0,79",
  "ICAEstacion" : "Bueno / Ona"
}, {
  "Date" : "17/01/2021",
  "Hour" : "15:00",
  "COmgm3" : "0,37",
  "CO8hmgm3" : "0,28",
  "NOgm3" : "8",
  "NO2" : "39",
  "NO2ICA" : "Muy bueno / Oso ona",
  "NOXgm3" : "52",
  "PM10" : "13,58",
  "PM10ICA" : "Muy bueno / Oso ona",
  "PM25" : "9,42",
  "PM25ICA" : "Muy bueno / Oso ona",
  "SO2" : "5",
  "SO2ICA" : "Muy bueno / Oso ona",
  "Dviengrados" : "151",
  "H" : "99",
  "TC" : "10,3",
  "Vvienms" : "1,01",
  "ICAEstacion" : "Muy bueno / Oso ona"
}, {
  "Date" : "17/01/2021",
  "Hour" : "14:00",
  "COmgm3" : "0,36",
  "CO8hmgm3" : "0,25",
  "NOgm3" : "12",
  "NO2" : "43",
  "NO2ICA" : "Bueno / Ona",
  "NOXgm3" : "60",
  "PM10" : "14,58",
  "PM10ICA" : "Muy bueno / Oso ona",
  "PM25" : "9,96",
  "PM25ICA" : "Muy bueno / Oso ona",
  "SO2" : "6",
  "SO2ICA" : "Muy bueno / Oso ona",
  "Dviengrados" : "158",
  "H" : "99",
  "TC" : "9,9",
  "Vvienms" : "1,03",
  "ICAEstacion" : "Bueno / Ona"
}, {
  "Date" : "17/01/2021",
  "Hour" : "13:00",
  "COmgm3" : "0,32",
  "CO8hmgm3" : "0,24",
  "NOgm3" : "11",
  "NO2" : "40",
  "NO2ICA" : "Muy bueno / Oso ona",
  "NOXgm3" : "56",
  "PM10" : "14,88",
  "PM10ICA" : "Muy bueno / Oso ona",
  "PM25ICA" : "Sin datos / Daturik gabe",
  "SO2" : "5",
  "SO2ICA" : "Muy bueno / Oso ona",
  "Dviengrados" : "162",
  "H" : "97",
  "TC" : "9",
  "Vvienms" : "1,68",
  "ICAEstacion" : "Muy bueno / Oso ona"
}, {
  "Date" : "17/01/2021",
  "Hour" : "12:00",
  "COmgm3" : "0,27",
  "CO8hmgm3" : "0,22",
  "NOgm3" : "6",
  "NO2" : "29",
  "NO2ICA" : "Muy bueno / Oso ona",
  "NOXgm3" : "38",
  "PM10" : "15,04",
  "PM10ICA" : "Muy bueno / Oso ona",
  "PM25ICA" : "Sin datos / Daturik gabe",
  "SO2" : "6",
  "SO2ICA" : "Muy bueno / Oso ona",
  "Dviengrados" : "152",
  "H" : "97",
  "TC" : "8,5",
  "Vvienms" : "1,67",
  "ICAEstacion" : "Muy bueno / Oso ona"
}, {
  "Date" : "17/01/2021",
  "Hour" : "11:00",
  "COmgm3" : "0,25",
  "CO8hmgm3" : "0,22",
  "NOgm3" : "3",
  "NO2" : "21",
  "NO2ICA" : "Muy bueno / Oso ona",
  "NOXgm3" : "25",
  "PM10" : "15,29",
  "PM10ICA" : "Muy bueno / Oso ona",
  "PM25ICA" : "Sin datos / Daturik gabe",
  "SO2" : "5",
  "SO2ICA" : "Muy bueno / Oso ona",
  "Dviengrados" : "79",
  "H" : "92",
  "TC" : "8,6",
  "Vvienms" : "0,98",
  "ICAEstacion" : "Muy bueno / Oso ona"
}, {
  "Date" : "17/01/2021",
  "Hour" : "10:00",
  "COmgm3" : "0,24",
  "CO8hmgm3" : "0,22",
  "NOgm3" : "3",
  "NO2" : "21",
  "NO2ICA" : "Muy bueno / Oso ona",
  "NOXgm3" : "25",
  "PM10" : "15,29",
  "PM10ICA" : "Muy bueno / Oso ona",
  "PM25ICA" : "Sin datos / Daturik gabe",
  "SO2" : "9",
  "SO2ICA" : "Muy bueno / Oso ona",
  "Dviengrados" : "63",
  "H" : "80",
  "TC" : "9,3",
  "Vvienms" : "0,73",
  "ICAEstacion" : "Muy bueno / Oso ona"
}, {
  "Date" : "17/01/2021",
  "Hour" : "09:00",
  "COmgm3" : "0,2",
  "CO8hmgm3" : "0,22",
  "NOgm3" : "3",
  "NO2" : "22",
  "NO2ICA" : "Muy bueno / Oso ona",
  "NOXgm3" : "26",
  "PM10" : "15,25",
  "PM10ICA" : "Muy bueno / Oso ona",
  "PM25" : "9,96",
  "PM25ICA" : "Muy bueno / Oso ona",
  "SO2" : "11",
  "SO2ICA" : "Muy bueno / Oso ona",
  "Dviengrados" : "136",
  "H" : "75",
  "TC" : "8,4",
  "Vvienms" : "0,62",
  "ICAEstacion" : "Muy bueno / Oso ona"
}, {
  "Date" : "17/01/2021",
  "Hour" : "08:00",
  "COmgm3" : "0,19",
  "CO8hmgm3" : "0,23",
  "NOgm3" : "2",
  "NO2" : "24",
  "NO2ICA" : "Muy bueno / Oso ona",
  "NOXgm3" : "26",
  "PM10" : "15,17",
  "PM10ICA" : "Muy bueno / Oso ona",
  "PM25" : "9,79",
  "PM25ICA" : "Muy bueno / Oso ona",
  "SO2" : "11",
  "SO2ICA" : "Muy bueno / Oso ona",
  "Dviengrados" : "157",
  "H" : "74",
  "TC" : "7,2",
  "Vvienms" : "1,52",
  "ICAEstacion" : "Muy bueno / Oso ona"
}, {
  "Date" : "17/01/2021",
  "Hour" : "07:00",
  "COmgm3" : "0,21",
  "CO8hmgm3" : "0,23",
  "NOgm3" : "4",
  "NO2" : "26",
  "NO2ICA" : "Muy bueno / Oso ona",
  "NOXgm3" : "31",
  "PM10" : "15,08",
  "PM10ICA" : "Muy bueno / Oso ona",
  "PM25" : "9,71",
  "PM25ICA" : "Muy bueno / Oso ona",
  "SO2" : "11",
  "SO2ICA" : "Muy bueno / Oso ona",
  "Dviengrados" : "154",
  "H" : "76",
  "TC" : "6,5",
  "Vvienms" : "1,96",
  "ICAEstacion" : "Muy bueno / Oso ona"
}, {
  "Date" : "17/01/2021",
  "Hour" : "06:00",
  "COmgm3" : "0,22",
  "CO8hmgm3" : "0,25",
  "NOgm3" : "3",
  "NO2" : "25",
  "NO2ICA" : "Muy bueno / Oso ona",
  "NOXgm3" : "29",
  "PM10" : "15,17",
  "PM10ICA" : "Muy bueno / Oso ona",
  "PM25" : "9,75",
  "PM25ICA" : "Muy bueno / Oso ona",
  "SO2" : "6",
  "SO2ICA" : "Muy bueno / Oso ona",
  "Dviengrados" : "179",
  "H" : "79",
  "TC" : "5,9",
  "Vvienms" : "0,99",
  "ICAEstacion" : "Muy bueno / Oso ona"
}, {
  "Date" : "17/01/2021",
  "Hour" : "05:00",
  "COmgm3" : "0,22",
  "CO8hmgm3" : "0,26",
  "NOgm3" : "3",
  "NO2" : "24",
  "NO2ICA" : "Muy bueno / Oso ona",
  "NOXgm3" : "27",
  "PM10" : "15,25",
  "PM10ICA" : "Muy bueno / Oso ona",
  "PM25" : "9,79",
  "PM25ICA" : "Muy bueno / Oso ona",
  "SO2" : "7",
  "SO2ICA" : "Muy bueno / Oso ona",
  "Dviengrados" : "219",
  "H" : "80",
  "TC" : "5,9",
  "Vvienms" : "0,48",
  "ICAEstacion" : "Muy bueno / Oso ona"
}, {
  "Date" : "17/01/2021",
  "Hour" : "04:00",
  "COmgm3" : "0,24",
  "CO8hmgm3" : "0,28",
  "NOgm3" : "2",
  "NO2" : "23",
  "NO2ICA" : "Muy bueno / Oso ona",
  "NOXgm3" : "26",
  "PM10" : "15,42",
  "PM10ICA" : "Muy bueno / Oso ona",
  "PM25" : "9,83",
  "PM25ICA" : "Muy bueno / Oso ona",
  "SO2" : "7",
  "SO2ICA" : "Muy bueno / Oso ona",
  "Dviengrados" : "175",
  "H" : "82",
  "TC" : "5,7",
  "Vvienms" : "1,01",
  "ICAEstacion" : "Muy bueno / Oso ona"
}, {
  "Date" : "17/01/2021",
  "Hour" : "03:00",
  "COmgm3" : "0,24",
  "CO8hmgm3" : "0,29",
  "NOgm3" : "2",
  "NO2" : "23",
  "NO2ICA" : "Muy bueno / Oso ona",
  "NOXgm3" : "26",
  "PM10" : "15,54",
  "PM10ICA" : "Muy bueno / Oso ona",
  "PM25" : "9,92",
  "PM25ICA" : "Muy bueno / Oso ona",
  "SO2" : "6",
  "SO2ICA" : "Muy bueno / Oso ona",
  "Dviengrados" : "185",
  "H" : "83",
  "TC" : "5,9",
  "Vvienms" : "0,46",
  "ICAEstacion" : "Muy bueno / Oso ona"
}, {
  "Date" : "17/01/2021",
  "Hour" : "02:00",
  "COmgm3" : "0,25",
  "CO8hmgm3" : "0,3",
  "NOgm3" : "2",
  "NO2" : "24",
  "NO2ICA" : "Muy bueno / Oso ona",
  "NOXgm3" : "26",
  "PM10" : "15,46",
  "PM10ICA" : "Muy bueno / Oso ona",
  "PM25" : "9,75",
  "PM25ICA" : "Muy bueno / Oso ona",
  "SO2" : "6",
  "SO2ICA" : "Muy bueno / Oso ona",
  "Dviengrados" : "83",
  "H" : "83",
  "TC" : "6,3",
  "Vvienms" : "0,28",
  "ICAEstacion" : "Muy bueno / Oso ona"
}, {
  "Date" : "17/01/2021",
  "Hour" : "01:00",
  "COmgm3" : "0,26",
  "CO8hmgm3" : "0,31",
  "NOgm3" : "1",
  "NO2" : "20",
  "NO2ICA" : "Muy bueno / Oso ona",
  "NOXgm3" : "21",
  "PM10" : "15,29",
  "PM10ICA" : "Muy bueno / Oso ona",
  "PM25" : "9,5",
  "PM25ICA" : "Muy bueno / Oso ona",
  "SO2" : "5",
  "SO2ICA" : "Muy bueno / Oso ona",
  "Dviengrados" : "126",
  "H" : "83",
  "TC" : "6,6",
  "Vvienms" : "0,07",
  "ICAEstacion" : "Muy bueno / Oso ona"
} ]