[ {
  "Date" : "18/01/2021",
  "Hour" : "24:00"
}, {
  "Date" : "18/01/2021",
  "Hour" : "23:00"
}, {
  "Date" : "18/01/2021",
  "Hour" : "22:00"
}, {
  "Date" : "18/01/2021",
  "Hour" : "21:00"
}, {
  "Date" : "18/01/2021",
  "Hour" : "20:00"
}, {
  "Date" : "18/01/2021",
  "Hour" : "19:00"
}, {
  "Date" : "18/01/2021",
  "Hour" : "18:00"
}, {
  "Date" : "18/01/2021",
  "Hour" : "17:00"
}, {
  "Date" : "18/01/2021",
  "Hour" : "16:00"
}, {
  "Date" : "18/01/2021",
  "Hour" : "15:00",
  "O3gm3" : "32",
  "OZONO" : "32",
  "O3ICA" : "Muy bueno / Oso ona",
  "O38hgm3" : "15",
  "Dviengrados" : "123",
  "H" : "73",
  "PmBar" : "959",
  "Precipitacionlm2" : "0",
  "Rwm2" : "217,5",
  "TC" : "11",
  "Vvienms" : "0,61",
  "ICAEstacion" : "Muy bueno / Oso ona"
}, {
  "Date" : "18/01/2021",
  "Hour" : "14:00",
  "O3gm3" : "25",
  "OZONO" : "25",
  "O3ICA" : "Muy bueno / Oso ona",
  "O38hgm3" : "11",
  "Dviengrados" : "80",
  "H" : "77",
  "PmBar" : "959,2",
  "Precipitacionlm2" : "0",
  "Rwm2" : "255,2",
  "TC" : "10,2",
  "Vvienms" : "0,79",
  "ICAEstacion" : "Muy bueno / Oso ona"
}, {
  "Date" : "18/01/2021",
  "Hour" : "13:00",
  "O3gm3" : "19",
  "OZONO" : "19",
  "O3ICA" : "Muy bueno / Oso ona",
  "O38hgm3" : "9",
  "Dviengrados" : "72",
  "H" : "81",
  "PmBar" : "959,8",
  "Precipitacionlm2" : "0",
  "Rwm2" : "222,4",
  "TC" : "9,3",
  "Vvienms" : "0,41",
  "ICAEstacion" : "Muy bueno / Oso ona"
}, {
  "Date" : "18/01/2021",
  "Hour" : "12:00",
  "O3gm3" : "12",
  "OZONO" : "12",
  "O3ICA" : "Muy bueno / Oso ona",
  "O38hgm3" : "8",
  "Dviengrados" : "84",
  "H" : "89",
  "PmBar" : "960,9",
  "Precipitacionlm2" : "0",
  "Rwm2" : "115,2",
  "TC" : "7,4",
  "Vvienms" : "0,48",
  "ICAEstacion" : "Muy bueno / Oso ona"
}, {
  "Date" : "18/01/2021",
  "Hour" : "11:00",
  "O3gm3" : "5",
  "OZONO" : "5",
  "O3ICA" : "Muy bueno / Oso ona",
  "O38hgm3" : "8",
  "Dviengrados" : "57",
  "H" : "92",
  "PmBar" : "961,3",
  "Precipitacionlm2" : "0",
  "Rwm2" : "109,8",
  "TC" : "6,8",
  "Vvienms" : "0,86",
  "ICAEstacion" : "Muy bueno / Oso ona"
}, {
  "Date" : "18/01/2021",
  "Hour" : "10:00",
  "O3gm3" : "3",
  "OZONO" : "3",
  "O3ICA" : "Muy bueno / Oso ona",
  "O38hgm3" : "11",
  "Dviengrados" : "54",
  "H" : "92",
  "PmBar" : "961,3",
  "Precipitacionlm2" : "0",
  "Rwm2" : "65,2",
  "TC" : "6,9",
  "Vvienms" : "0,28",
  "ICAEstacion" : "Muy bueno / Oso ona"
}, {
  "Date" : "18/01/2021",
  "Hour" : "09:00",
  "O3gm3" : "2",
  "OZONO" : "2",
  "O3ICA" : "Muy bueno / Oso ona",
  "O38hgm3" : "15",
  "Dviengrados" : "274",
  "H" : "95",
  "PmBar" : "961,3",
  "Precipitacionlm2" : "0",
  "Rwm2" : "15,1",
  "TC" : "6",
  "Vvienms" : "0,37",
  "ICAEstacion" : "Muy bueno / Oso ona"
}, {
  "Date" : "18/01/2021",
  "Hour" : "08:00",
  "O3gm3" : "2",
  "OZONO" : "2",
  "O3ICA" : "Muy bueno / Oso ona",
  "O38hgm3" : "17",
  "Dviengrados" : "66",
  "H" : "93",
  "PmBar" : "961,2",
  "Precipitacionlm2" : "0",
  "Rwm2" : "0,3",
  "TC" : "6,2",
  "Vvienms" : "0,35",
  "ICAEstacion" : "Muy bueno / Oso ona"
}, {
  "Date" : "18/01/2021",
  "Hour" : "07:00",
  "O3gm3" : "7",
  "OZONO" : "7",
  "O3ICA" : "Muy bueno / Oso ona",
  "O38hgm3" : "22",
  "Dviengrados" : "8",
  "H" : "95",
  "PmBar" : "961,1",
  "Precipitacionlm2" : "0",
  "Rwm2" : "0",
  "TC" : "6",
  "Vvienms" : "0,18",
  "ICAEstacion" : "Muy bueno / Oso ona"
}, {
  "Date" : "18/01/2021",
  "Hour" : "06:00",
  "O3gm3" : "16",
  "OZONO" : "16",
  "O3ICA" : "Muy bueno / Oso ona",
  "O38hgm3" : "27",
  "Dviengrados" : "206",
  "H" : "96",
  "PmBar" : "961",
  "Precipitacionlm2" : "0",
  "Rwm2" : "0",
  "TC" : "5,6",
  "Vvienms" : "0,16",
  "ICAEstacion" : "Muy bueno / Oso ona"
}, {
  "Date" : "18/01/2021",
  "Hour" : "05:00",
  "O3gm3" : "17",
  "OZONO" : "17",
  "O3ICA" : "Muy bueno / Oso ona",
  "O38hgm3" : "32",
  "Dviengrados" : "73",
  "H" : "97",
  "PmBar" : "960,9",
  "Precipitacionlm2" : "0",
  "Rwm2" : "0",
  "TC" : "5,4",
  "Vvienms" : "0,54",
  "ICAEstacion" : "Muy bueno / Oso ona"
}, {
  "Date" : "18/01/2021",
  "Hour" : "04:00",
  "O3gm3" : "24",
  "OZONO" : "24",
  "O3ICA" : "Muy bueno / Oso ona",
  "O38hgm3" : "35",
  "Dviengrados" : "93",
  "H" : "96",
  "PmBar" : "961,1",
  "Precipitacionlm2" : "0",
  "Rwm2" : "0",
  "TC" : "5,2",
  "Vvienms" : "0,39",
  "ICAEstacion" : "Muy bueno / Oso ona"
}, {
  "Date" : "18/01/2021",
  "Hour" : "03:00",
  "O3gm3" : "36",
  "OZONO" : "36",
  "O3ICA" : "Muy bueno / Oso ona",
  "O38hgm3" : "37",
  "Dviengrados" : "238",
  "H" : "93",
  "PmBar" : "961,2",
  "Precipitacionlm2" : "0",
  "Rwm2" : "0",
  "TC" : "6,9",
  "Vvienms" : "0,57",
  "ICAEstacion" : "Muy bueno / Oso ona"
}, {
  "Date" : "18/01/2021",
  "Hour" : "02:00",
  "O3ICA" : "Sin datos / Daturik gabe",
  "O38hgm3" : "37",
  "Dviengrados" : "247",
  "H" : "91",
  "PmBar" : "961,5",
  "Precipitacionlm2" : "0",
  "Rwm2" : "0",
  "TC" : "7,7",
  "Vvienms" : "0,74",
  "ICAEstacion" : "Sin datos / Daturik gabe"
}, {
  "Date" : "18/01/2021",
  "Hour" : "01:00",
  "O3gm3" : "35",
  "OZONO" : "35",
  "O3ICA" : "Muy bueno / Oso ona",
  "O38hgm3" : "37",
  "Dviengrados" : "235",
  "H" : "92",
  "PmBar" : "961,8",
  "Precipitacionlm2" : "0",
  "Rwm2" : "0",
  "TC" : "7,6",
  "Vvienms" : "0,87",
  "ICAEstacion" : "Muy bueno / Oso ona"
}, {
  "Date" : "17/01/2021",
  "Hour" : "24:00",
  "O3gm3" : "38",
  "OZONO" : "38",
  "O3ICA" : "Muy bueno / Oso ona",
  "O38hgm3" : "38",
  "Dviengrados" : "237",
  "H" : "94",
  "PmBar" : "962,2",
  "Precipitacionlm2" : "0",
  "Rwm2" : "0",
  "TC" : "7,9",
  "Vvienms" : "0,52",
  "ICAEstacion" : "Muy bueno / Oso ona"
}, {
  "Date" : "17/01/2021",
  "Hour" : "23:00",
  "O3gm3" : "41",
  "OZONO" : "41",
  "O3ICA" : "Muy bueno / Oso ona",
  "O38hgm3" : "36",
  "Dviengrados" : "290",
  "H" : "95",
  "PmBar" : "962,2",
  "Precipitacionlm2" : "0",
  "Rwm2" : "0",
  "TC" : "8,1",
  "Vvienms" : "0,62",
  "ICAEstacion" : "Muy bueno / Oso ona"
}, {
  "Date" : "17/01/2021",
  "Hour" : "22:00",
  "O3gm3" : "40",
  "OZONO" : "40",
  "O3ICA" : "Muy bueno / Oso ona",
  "O38hgm3" : "34",
  "Dviengrados" : "297",
  "H" : "96",
  "PmBar" : "962,1",
  "Precipitacionlm2" : "0,1",
  "Rwm2" : "0",
  "TC" : "8,1",
  "Vvienms" : "0,79",
  "ICAEstacion" : "Muy bueno / Oso ona"
}, {
  "Date" : "17/01/2021",
  "Hour" : "21:00",
  "O3gm3" : "36",
  "OZONO" : "36",
  "O3ICA" : "Muy bueno / Oso ona",
  "O38hgm3" : "32",
  "Dviengrados" : "275",
  "H" : "95",
  "PmBar" : "962",
  "Precipitacionlm2" : "0,1",
  "Rwm2" : "0",
  "TC" : "8,3",
  "Vvienms" : "1,04",
  "ICAEstacion" : "Muy bueno / Oso ona"
}, {
  "Date" : "17/01/2021",
  "Hour" : "20:00",
  "O3gm3" : "30",
  "OZONO" : "30",
  "O3ICA" : "Muy bueno / Oso ona",
  "O38hgm3" : "31",
  "Dviengrados" : "276",
  "H" : "95",
  "PmBar" : "962,1",
  "Precipitacionlm2" : "0,1",
  "Rwm2" : "0",
  "TC" : "8,5",
  "Vvienms" : "0,9",
  "ICAEstacion" : "Muy bueno / Oso ona"
}, {
  "Date" : "17/01/2021",
  "Hour" : "19:00",
  "O3gm3" : "35",
  "OZONO" : "35",
  "O3ICA" : "Muy bueno / Oso ona",
  "O38hgm3" : "29",
  "Dviengrados" : "269",
  "H" : "95",
  "PmBar" : "962",
  "Precipitacionlm2" : "0",
  "Rwm2" : "0",
  "TC" : "8,4",
  "Vvienms" : "1,13",
  "ICAEstacion" : "Muy bueno / Oso ona"
}, {
  "Date" : "17/01/2021",
  "Hour" : "18:00",
  "O3gm3" : "37",
  "OZONO" : "37",
  "O3ICA" : "Muy bueno / Oso ona",
  "O38hgm3" : "27",
  "Dviengrados" : "267",
  "H" : "94",
  "PmBar" : "961,8",
  "Precipitacionlm2" : "0",
  "Rwm2" : "0,8",
  "TC" : "8,5",
  "Vvienms" : "1,1",
  "ICAEstacion" : "Muy bueno / Oso ona"
}, {
  "Date" : "17/01/2021",
  "Hour" : "17:00",
  "O3gm3" : "34",
  "OZONO" : "34",
  "O3ICA" : "Muy bueno / Oso ona",
  "O38hgm3" : "25",
  "Dviengrados" : "269",
  "H" : "92",
  "PmBar" : "961,6",
  "Precipitacionlm2" : "0",
  "Rwm2" : "33,6",
  "TC" : "8,6",
  "Vvienms" : "1,11",
  "ICAEstacion" : "Muy bueno / Oso ona"
}, {
  "Date" : "17/01/2021",
  "Hour" : "16:00",
  "O3gm3" : "23",
  "OZONO" : "23",
  "O3ICA" : "Muy bueno / Oso ona",
  "O38hgm3" : "22",
  "Dviengrados" : "326",
  "H" : "87",
  "PmBar" : "961,5",
  "Precipitacionlm2" : "0",
  "Rwm2" : "60,9",
  "TC" : "9,2",
  "Vvienms" : "0,27",
  "ICAEstacion" : "Muy bueno / Oso ona"
}, {
  "Date" : "17/01/2021",
  "Hour" : "15:00",
  "O3gm3" : "26",
  "OZONO" : "26",
  "O3ICA" : "Muy bueno / Oso ona",
  "O38hgm3" : "21",
  "Dviengrados" : "78",
  "H" : "84",
  "PmBar" : "961,3",
  "Precipitacionlm2" : "0",
  "Rwm2" : "107,6",
  "TC" : "8,5",
  "Vvienms" : "0,58",
  "ICAEstacion" : "Muy bueno / Oso ona"
}, {
  "Date" : "17/01/2021",
  "Hour" : "14:00",
  "O3gm3" : "24",
  "OZONO" : "24",
  "O3ICA" : "Muy bueno / Oso ona",
  "O38hgm3" : "20",
  "Dviengrados" : "53",
  "H" : "71",
  "PmBar" : "961,4",
  "Precipitacionlm2" : "0",
  "Rwm2" : "150,6",
  "TC" : "8,7",
  "Vvienms" : "0,91",
  "ICAEstacion" : "Muy bueno / Oso ona"
}, {
  "Date" : "17/01/2021",
  "Hour" : "13:00",
  "O3gm3" : "26",
  "OZONO" : "26",
  "O3ICA" : "Muy bueno / Oso ona",
  "O38hgm3" : "19",
  "Dviengrados" : "13",
  "H" : "61",
  "PmBar" : "961,8",
  "Precipitacionlm2" : "0",
  "Rwm2" : "220,5",
  "TC" : "9,7",
  "Vvienms" : "0,36",
  "ICAEstacion" : "Muy bueno / Oso ona"
}, {
  "Date" : "17/01/2021",
  "Hour" : "12:00",
  "O3gm3" : "15",
  "OZONO" : "15",
  "O3ICA" : "Muy bueno / Oso ona",
  "O38hgm3" : "18",
  "Dviengrados" : "48",
  "H" : "65",
  "PmBar" : "962,6",
  "Precipitacionlm2" : "0",
  "Rwm2" : "156,4",
  "TC" : "7,6",
  "Vvienms" : "0,62",
  "ICAEstacion" : "Muy bueno / Oso ona"
}, {
  "Date" : "17/01/2021",
  "Hour" : "11:00",
  "O3gm3" : "21",
  "OZONO" : "21",
  "O3ICA" : "Muy bueno / Oso ona",
  "O38hgm3" : "19",
  "Dviengrados" : "296",
  "H" : "67",
  "PmBar" : "962,8",
  "Precipitacionlm2" : "0",
  "Rwm2" : "126,2",
  "TC" : "6,6",
  "Vvienms" : "0,35",
  "ICAEstacion" : "Muy bueno / Oso ona"
}, {
  "Date" : "17/01/2021",
  "Hour" : "10:00",
  "O3gm3" : "17",
  "OZONO" : "17",
  "O3ICA" : "Muy bueno / Oso ona",
  "O38hgm3" : "19",
  "Dviengrados" : "278",
  "H" : "71",
  "PmBar" : "962,4",
  "Precipitacionlm2" : "0",
  "Rwm2" : "85,9",
  "TC" : "4,8",
  "Vvienms" : "0,21",
  "ICAEstacion" : "Muy bueno / Oso ona"
}, {
  "Date" : "17/01/2021",
  "Hour" : "09:00",
  "O3gm3" : "16",
  "OZONO" : "16",
  "O3ICA" : "Muy bueno / Oso ona",
  "O38hgm3" : "19",
  "Dviengrados" : "261",
  "H" : "75",
  "PmBar" : "962,1",
  "Precipitacionlm2" : "0",
  "Rwm2" : "38,5",
  "TC" : "3,1",
  "Vvienms" : "0,42",
  "ICAEstacion" : "Muy bueno / Oso ona"
}, {
  "Date" : "17/01/2021",
  "Hour" : "08:00",
  "O3gm3" : "19",
  "OZONO" : "19",
  "O3ICA" : "Muy bueno / Oso ona",
  "O38hgm3" : "20",
  "Dviengrados" : "163",
  "H" : "79",
  "PmBar" : "962,2",
  "Precipitacionlm2" : "0",
  "Rwm2" : "0,9",
  "TC" : "1,9",
  "Vvienms" : "0,38",
  "ICAEstacion" : "Muy bueno / Oso ona"
}, {
  "Date" : "17/01/2021",
  "Hour" : "07:00",
  "O3gm3" : "15",
  "OZONO" : "15",
  "O3ICA" : "Muy bueno / Oso ona",
  "O38hgm3" : "21",
  "Dviengrados" : "246",
  "H" : "82",
  "PmBar" : "961,7",
  "Precipitacionlm2" : "0",
  "Rwm2" : "0",
  "TC" : "1,2",
  "Vvienms" : "0,58",
  "ICAEstacion" : "Muy bueno / Oso ona"
}, {
  "Date" : "17/01/2021",
  "Hour" : "06:00",
  "O3gm3" : "22",
  "OZONO" : "22",
  "O3ICA" : "Muy bueno / Oso ona",
  "O38hgm3" : "23",
  "Dviengrados" : "73",
  "H" : "81",
  "PmBar" : "961,3",
  "Precipitacionlm2" : "0",
  "Rwm2" : "0",
  "TC" : "1,5",
  "Vvienms" : "0,61",
  "ICAEstacion" : "Muy bueno / Oso ona"
}, {
  "Date" : "17/01/2021",
  "Hour" : "05:00",
  "O3gm3" : "21",
  "OZONO" : "21",
  "O3ICA" : "Muy bueno / Oso ona",
  "O38hgm3" : "24",
  "Dviengrados" : "7",
  "H" : "79",
  "PmBar" : "961,1",
  "Precipitacionlm2" : "0",
  "Rwm2" : "0",
  "TC" : "1,6",
  "Vvienms" : "0,31",
  "ICAEstacion" : "Muy bueno / Oso ona"
}, {
  "Date" : "17/01/2021",
  "Hour" : "04:00",
  "O3gm3" : "22",
  "OZONO" : "22",
  "O3ICA" : "Muy bueno / Oso ona",
  "O38hgm3" : "23",
  "Dviengrados" : "223",
  "H" : "81",
  "PmBar" : "961,3",
  "Precipitacionlm2" : "0",
  "Rwm2" : "0",
  "TC" : "1,4",
  "Vvienms" : "0,58",
  "ICAEstacion" : "Muy bueno / Oso ona"
}, {
  "Date" : "17/01/2021",
  "Hour" : "03:00",
  "O3gm3" : "21",
  "OZONO" : "21",
  "O3ICA" : "Muy bueno / Oso ona",
  "O38hgm3" : "23",
  "Dviengrados" : "68",
  "H" : "79",
  "PmBar" : "961,6",
  "Precipitacionlm2" : "0",
  "Rwm2" : "0",
  "TC" : "2,4",
  "Vvienms" : "0,46",
  "ICAEstacion" : "Muy bueno / Oso ona"
}, {
  "Date" : "17/01/2021",
  "Hour" : "02:00",
  "O3ICA" : "Sin datos / Daturik gabe",
  "O38hgm3" : "24",
  "Dviengrados" : "271",
  "H" : "75",
  "PmBar" : "961,6",
  "Precipitacionlm2" : "0",
  "Rwm2" : "0",
  "TC" : "2,9",
  "Vvienms" : "0,41",
  "ICAEstacion" : "Sin datos / Daturik gabe"
}, {
  "Date" : "17/01/2021",
  "Hour" : "01:00",
  "O3gm3" : "26",
  "OZONO" : "26",
  "O3ICA" : "Muy bueno / Oso ona",
  "O38hgm3" : "24",
  "Dviengrados" : "278",
  "H" : "74",
  "PmBar" : "961,9",
  "Precipitacionlm2" : "0",
  "Rwm2" : "0",
  "TC" : "3,3",
  "Vvienms" : "0,26",
  "ICAEstacion" : "Muy bueno / Oso ona"
} ]